README.md
setup.py
pdf_config.egg-info/PKG-INFO
pdf_config.egg-info/SOURCES.txt
pdf_config.egg-info/dependency_links.txt
pdf_config.egg-info/entry_points.txt
pdf_config.egg-info/requires.txt
pdf_config.egg-info/top_level.txt
pdfconfig/__init__.py
pdfconfig/composer.py
pdfconfig/main.py
pdfconfig/utils.py