Metadata-Version: 1.1
Name: pdf-config
Version: 1.0.0
Summary: Merges PDF files into one using a YAML configuration file.
Home-page: https://github.com/merll/pdf-config
Author: Matthias Erll
Author-email: matthias@erll.de
License: MIT
Keywords: pdf,yaml
Platform: OS Independent
Classifier: License :: OSI Approved :: MIT License
Classifier: Operating System :: OS Independent
Classifier: Programming Language :: Python
Classifier: Development Status :: 5 - Production/Stable
Classifier: Programming Language :: Python :: 3.6
Classifier: Programming Language :: Python :: 3.7
Classifier: Programming Language :: Python :: 3.8
